saferequests/__init__.py
saferequests/datamodels.py
saferequests/logging.py
saferequests/methods.py
saferequests/proxyrotation/__init__.py
saferequests/proxyrotation/repository/__init__.py
saferequests/proxyrotation/repository/asyncio.py
saferequests/proxyrotation/rotator.py
saferequests/sessions.py
saferequests-0.1.0.dist-info/LICENSE
saferequests-0.1.0.dist-info/METADATA
saferequests-0.1.0.dist-info/WHEEL
saferequests-0.1.0.dist-info/RECORD
